{"therock": {"current": "78195385", "value": -7819529609668413744895, "previous": "7819529609668491940280"}, "cristiano": {"current": "91612882", "value": 84, "previous": "91612798"}, "instagram": {"current": "213984155", "value": 131, "previous": "213984024"}, "arianagrande": {"current": "97874073", "value": 138, "previous": "97873935"}, "kyliejenner": {"current": "87079122", "value": 68, "previous": "87079054"}, "beyonce": {"current": "95653037", "value": 68, "previous": "95652969"}, "taylorswift": {"current": "98056467", "value": 21, "previous": "98056446"}, "kimkardashian": {"current": "93379365", "value": 95, "previous": "93379270"}, "justinbieber": {"current": "78518785", "value": -20, "previous": "78518805"}, "selenagomez": {"current": "111207554", "value": 142, "previous": "111207412"}}